magic 03f30d0a
moddate 79c2a95d (Fri Oct 18 19:17:37 2019)
code
   argcount 0
   nlocals 0
   stacksize 2
   flags 0040
   code
      6400005a00006401005a0100650000650100185a02006502004748640200
      53
  1           0 LOAD_CONST               0 (2)
              3 STORE_NAME               0 (a)

  2           6 LOAD_CONST               1 (3)
              9 STORE_NAME               1 (b)

  4          12 LOAD_NAME                0 (a)
             15 LOAD_NAME                1 (b)
             18 BINARY_SUBTRACT     
             19 STORE_NAME               2 (c)

  6          22 LOAD_NAME                2 (c)
             25 PRINT_ITEM          
             26 PRINT_NEWLINE       
             27 LOAD_CONST               2 (None)
             30 RETURN_VALUE        
   consts
      2
      3
      None
   names ('a', 'b', 'c')
   varnames ()
   freevars ()
   cellvars ()
   filename 'sub/sub.py'
   name '<module>'
   firstlineno 1
   lnotab 060106020a02
